snp_caller/__init__.py
snp_caller/model/__init__.py
snp_caller/model/locus.py
snp_caller/model/read_pair.py
snp_caller/model/variant_candidate.py
snp_caller/model/variant_candidate_collection.py
snp_caller/tools/__init__.py
snp_caller/tools/batchy_mapper.py
snp_caller/tools/batchy_snp_caller.py
snp_caller/tools/get_variant_calls.py
snp_caller/tools/redis_locus_saver.py
snp_caller/util/__init__.py
snp_caller/util/logging.py
snp_caller-0.0.1.dist-info/METADATA
snp_caller-0.0.1.dist-info/WHEEL
snp_caller-0.0.1.dist-info/top_level.txt
snp_caller-0.0.1.dist-info/RECORD
